gdbd_probablity
