Metadata-Version: 2.1
Name: gdbd-probablity
Version: 1.0
Summary: Gaussian ,General and binomial distributions
Author: Amit Ranjan
Author-email: amitranjan1139@gmail.com
